{
  "type": "object",
  "name": "GetValuesforAllPicklistFieldsofaRecordType",
  "properties": {
    "eTag": {
      "type": "string"
    },
    "picklistFieldValues": {
      "type": "object",
      "properties": {
        "CleanStatus": {
          "type": "object",
          "properties": {
            "controllerValues": {
              "type": "object"
            },
            "defaultValue": {
              "type": "['string', 'null']"
            },
            "eTag": {
              "type": "string"
            },
            "url": {
              "type": "string"
            },
            "values": {
              "type": "array",
              "description": "",
              "items": {
                "type": "object",
                "properties": {
                  "attributes": {
                    "type": "['string', 'null']"
                  },
                  "label": {
                    "type": "string"
                  },
                  "validFor": {
                    "type": "array",
                    "description": "",
                    "items": {
                      "type": "object"
                    }
                  },
                  "value": {
                    "type": "string"
                  }
                },
                "required": [
                  "attributes",
                  "label",
                  "validFor",
                  "value"
                ]
              }
            }
          },
          "required": [
            "controllerValues",
            "defaultValue",
            "eTag",
            "url",
            "values"
          ]
        },
        "LeadSource": {
          "type": "object",
          "properties": {
            "controllerValues": {
              "type": "object"
            },
            "defaultValue": {
              "type": "['string', 'null']"
            },
            "eTag": {
              "type": "string"
            },
            "url": {
              "type": "string"
            },
            "values": {
              "type": "array",
              "description": "",
              "items": {
                "type": "object",
                "properties": {
                  "attributes": {
                    "type": "['string', 'null']"
                  },
                  "label": {
                    "type": "string"
                  },
                  "validFor": {
                    "type": "array",
                    "description": "",
                    "items": {
                      "type": "object"
                    }
                  },
                  "value": {
                    "type": "string"
                  }
                },
                "required": [
                  "attributes",
                  "label",
                  "validFor",
                  "value"
                ]
              }
            }
          },
          "required": [
            "controllerValues",
            "defaultValue",
            "eTag",
            "url",
            "values"
          ]
        },
        "Level__c": {
          "type": "object",
          "properties": {
            "controllerValues": {
              "type": "object"
            },
            "defaultValue": {
              "type": "['string', 'null']"
            },
            "eTag": {
              "type": "string"
            },
            "url": {
              "type": "string"
            },
            "values": {
              "type": "array",
              "description": "",
              "items": {
                "type": "object",
                "properties": {
                  "attributes": {
                    "type": "['string', 'null']"
                  },
                  "label": {
                    "type": "string"
                  },
                  "validFor": {
                    "type": "array",
                    "description": "",
                    "items": {
                      "type": "object"
                    }
                  },
                  "value": {
                    "type": "string"
                  }
                },
                "required": [
                  "attributes",
                  "label",
                  "validFor",
                  "value"
                ]
              }
            }
          },
          "required": [
            "controllerValues",
            "defaultValue",
            "eTag",
            "url",
            "values"
          ]
        },
        "MailingGeocodeAccuracy": {
          "type": "object",
          "properties": {
            "controllerValues": {
              "type": "object"
            },
            "defaultValue": {
              "type": "['string', 'null']"
            },
            "eTag": {
              "type": "string"
            },
            "url": {
              "type": "string"
            },
            "values": {
              "type": "array",
              "description": "",
              "items": {
                "type": "object",
                "properties": {
                  "attributes": {
                    "type": "['string', 'null']"
                  },
                  "label": {
                    "type": "string"
                  },
                  "validFor": {
                    "type": "array",
                    "description": "",
                    "items": {
                      "type": "object"
                    }
                  },
                  "value": {
                    "type": "string"
                  }
                },
                "required": [
                  "attributes",
                  "label",
                  "validFor",
                  "value"
                ]
              }
            }
          },
          "required": [
            "controllerValues",
            "defaultValue",
            "eTag",
            "url",
            "values"
          ]
        },
        "OtherGeocodeAccuracy": {
          "type": "object",
          "properties": {
            "controllerValues": {
              "type": "object"
            },
            "defaultValue": {
              "type": "['string', 'null']"
            },
            "eTag": {
              "type": "string"
            },
            "url": {
              "type": "string"
            },
            "values": {
              "type": "array",
              "description": "",
              "items": {
                "type": "object",
                "properties": {
                  "attributes": {
                    "type": "['string', 'null']"
                  },
                  "label": {
                    "type": "string"
                  },
                  "validFor": {
                    "type": "array",
                    "description": "",
                    "items": {
                      "type": "object"
                    }
                  },
                  "value": {
                    "type": "string"
                  }
                },
                "required": [
                  "attributes",
                  "label",
                  "validFor",
                  "value"
                ]
              }
            }
          },
          "required": [
            "controllerValues",
            "defaultValue",
            "eTag",
            "url",
            "values"
          ]
        },
        "Salutation": {
          "type": "object",
          "properties": {
            "controllerValues": {
              "type": "object"
            },
            "defaultValue": {
              "type": "['string', 'null']"
            },
            "eTag": {
              "type": "string"
            },
            "url": {
              "type": "string"
            },
            "values": {
              "type": "array",
              "description": "",
              "items": {
                "type": "object",
                "properties": {
                  "attributes": {
                    "type": "['string', 'null']"
                  },
                  "label": {
                    "type": "string"
                  },
                  "validFor": {
                    "type": "array",
                    "description": "",
                    "items": {
                      "type": "object"
                    }
                  },
                  "value": {
                    "type": "string"
                  }
                },
                "required": [
                  "attributes",
                  "label",
                  "validFor",
                  "value"
                ]
              }
            }
          },
          "required": [
            "controllerValues",
            "defaultValue",
            "eTag",
            "url",
            "values"
          ]
        }
      },
      "required": [
        "CleanStatus",
        "LeadSource",
        "Level__c",
        "MailingGeocodeAccuracy",
        "OtherGeocodeAccuracy",
        "Salutation"
      ]
    }
  },
  "required": [
    "eTag",
    "picklistFieldValues"
  ],
  "$schema": "https://json-structure.org/draft/2020-12/schema"
}